setup.py
SimpleAES/__init__.py
SimpleAES/exceptions.py
SimpleAES/version.py
SimpleAES.egg-info/PKG-INFO
SimpleAES.egg-info/SOURCES.txt
SimpleAES.egg-info/dependency_links.txt
SimpleAES.egg-info/not-zip-safe
SimpleAES.egg-info/requires.txt
SimpleAES.egg-info/top_level.txt